gdtms/__init__.py
gdtms/schema.py
gdtms/data/adjectives.json
gdtms/data/cities.json
gdtms/data/domains.json
gdtms/data/names.json
gdtms/data/nouns.json
gdtms/data/proverbs.json
gdtms/data/surnames.json
gdtms/data/verbs.json
gdtms/data_types/address.py
gdtms/data_types/adjective.py
gdtms/data_types/autoincrement.py
gdtms/data_types/city.py
gdtms/data_types/composite.py
gdtms/data_types/data_type.py
gdtms/data_types/date.py
gdtms/data_types/domain_name.py
gdtms/data_types/email.py
gdtms/data_types/first_name.py
gdtms/data_types/hardcoded_value.py
gdtms/data_types/last_name.py
gdtms/data_types/list_item.py
gdtms/data_types/noun.py
gdtms/data_types/number.py
gdtms/data_types/phone_number.py
gdtms/data_types/proverb.py
gdtms/data_types/reference.py
gdtms/data_types/timestamp.py
gdtms/data_types/undefined.py
gdtms/data_types/url.py
gdtms/data_types/uuid.py
gdtms/data_types/verb.py
gdtms/data_types/zip_postal.py
gdtms/entities/field.py
gdtms/entities/record.py
gdtms/entities/schema.py
gdtms/entities/table.py
gdtms/entities/unique_key.py
gdtms/exceptions/__init__.py
gdtms/exceptions/base_exception.py
gdtms/exceptions/missing_dependency_tables.py
gdtms/exceptions/no_records_generated_yet_exception.py
gdtms/exceptions/timout_exceeded.py
gdtms/sources/sources.py
gdtms/views/mysql.py
gdtms/views/view.py
generated_data_that_makes_sense-1.0.0.dist-info/licenses/LICENSE
generated_data_that_makes_sense-1.0.0.dist-info/METADATA
generated_data_that_makes_sense-1.0.0.dist-info/WHEEL
generated_data_that_makes_sense-1.0.0.dist-info/top_level.txt
generated_data_that_makes_sense-1.0.0.dist-info/RECORD
