Metadata-Version: 2.4
Name: generated-data-that-makes-sense
Version: 1.0.0
Summary: Relational data generator that creates meaningful test data with referential integrity
Author-email: Dmitry Smolovich <dsmolovich@gmail.com>
Project-URL: Homepage, https://github.com/dsmolovich/generated-data-that-makes-sense
Project-URL: Repository, https://github.com/dsmolovich/generated-data-that-makes-sense
Keywords: testing,generator,data,relational,database,mysql
Classifier: Development Status :: 4 - Beta
Classifier: Intended Audience :: Developers
Classifier: Programming Language :: Python :: 3
Classifier: Programming Language :: Python :: 3.8
Classifier: Programming Language :: Python :: 3.9
Classifier: Programming Language :: Python :: 3.10
Classifier: Programming Language :: Python :: 3.11
Classifier: Programming Language :: Python :: 3.12
Classifier: Programming Language :: Python :: 3.13
Classifier: Topic :: Database
Classifier: Topic :: Software Development :: Testing
Requires-Python: >=3.8
License-File: LICENSE
Dynamic: license-file
